{
  "code": 200,
  "data": {
    "email": "9854211@163.com",
    "jobs": [
      {
        "id": 1,
        "name": "标书制作专员",
        "englishName": "Tender preparation specialist",
        "responsibilities": [
          "负责工程项目的报名，资格预审及投标文件的编写、制作、汇总等;",
          "核实业务部门人员的投标价格工作，完成标书制作;",
          "配合与招标公司的联络，投标项目执行过程中与业主的沟通，协助投标项目的有效执行;",
          "对标书、合同的技术规范进行审核、确认;",
          "按时装订、保存、投交标书，确保标书保密性，完整性、正确性，规范及美观的及时递交客户;",
          "对于招标文件的澄清文件，及时进行汇总、运用等工作;",
          "负责投标文件和客户信息资料的整理，确保文件准确性、完整性、保密性;",
          "配合协助其他部门完成领导交办的其他工作."
        ],
        "requirements": [
          "工程造价、信息化专业优先"
        ],
        "benefits": [
          "五险一金"
        ],
        "show": true
      },
      {
        "id": 2,
        "name": "标书制作专员",
        "englishName": "Tender preparation specialist",
        "responsibilities": [
          "负责工程项目的报名，资格预审及投标文件的编写、制作、汇总等;",
          "核实业务部门人员的投标价格工作，完成标书制作;",
          "配合与招标公司的联络，投标项目执行过程中与业主的沟通，协助投标项目的有效执行;",
          "对标书、合同的技术规范进行审核、确认;",
          "按时装订、保存、投交标书，确保标书保密性，完整性、正确性，规范及美观的及时递交客户;",
          "对于招标文件的澄清文件，及时进行汇总、运用等工作;",
          "负责投标文件和客户信息资料的整理，确保文件准确性、完整性、保密性;",
          "配合协助其他部门完成领导交办的其他工作."
        ],
        "requirements": [
          "工程造价、信息化专业优先"
        ],
        "benefits": [
          "五险一金"
        ],
        "show": true
      }
    ]
  },
  "message": "成功"
}
